rule_of_thumb/__init__.py
rule_of_thumb/beam_design.py
rule_of_thumb/bracket_corbel_aci.py
rule_of_thumb/bulk_density.py
rule_of_thumb/cal_moment.py
rule_of_thumb/dsg_bm_aci.py
rule_of_thumb/dsg_bm_new_temp.py
rule_of_thumb/geo_solver.py
rule_of_thumb/pavement_des.py
rule_of_thumb/pipes.py
rule_of_thumb/sandy_str_cals.py
rule_of_thumb/self_weight.py
rule_of_thumb/shapes_properties.py
rule_of_thumb/simple_beam_moment.py
rule_of_thumb/slab_thickness.py
rule_of_thumb/soil_loads.py
rule_of_thumb/wtr_m11_cals.py
rule_of_thumb-0.1.4.5.dist-info/METADATA
rule_of_thumb-0.1.4.5.dist-info/WHEEL
rule_of_thumb-0.1.4.5.dist-info/top_level.txt
rule_of_thumb-0.1.4.5.dist-info/RECORD
