Metadata-Version: 2.2
Name: rule_of_thumb
Version: 0.1.4.5
Summary: A package containing structural engineering rules of thumb
Home-page: https://github.com/yourusername/rule_of_thumb
Author: Mario Samaan
Classifier: Programming Language :: Python :: 3
Classifier: License :: OSI Approved :: MIT License
Dynamic: author
Dynamic: classifier
Dynamic: home-page
Dynamic: summary
